{
    "name": "Albany, NY",
    "description": "openAlbany supports government transparency, openness and innovative uses of municipal data that can help improve the lives of Albany residents, visitors and businesses.",
    "image": "http:\/\/kinlane-productions.s3.amazonaws.com\/api-evangelist-site\/company\/logos\/openalbany-logo.png",
    "tags": [
        "city government",
        "data provider",
        "have api",
        "profile"
    ],
    "created": "2019-12-20",
    "modified": "2019-12-20",
    "url": "https:\/\/raw.githubusercontent.com\/api-evangelist\/albany-ny\/master\/apis.json",
    "specificationVersion": "0.14",
    "apis": [
        {
            "name": "Albany, NY",
            "description": null,
            "image": "http:\/\/kinlane-productions.s3.amazonaws.com\/api-evangelist-site\/company\/logos\/openalbany-logo.png",
            "humanURL": "https:\/\/data.albanyny.gov\/",
            "baseURL": "",
            "tags": [],
            "properties": [
                {
                    "type": "x-openapi",
                    "url": "https:\/\/raw.githubusercontent.com\/api-evangelist\/albany-ny\/master\/albany-ny-openapi.json"
                }
            ]
        }
    ],
    "include": [],
    "x-common": [
        {
            "type": "APIs.json",
            "url": "https:\/\/raw.githubusercontent.com\/api-evangelist\/1forge\/master\/apis.json"
        },
        {
            "type": "Website",
            "url": "https:\/\/data.albanyny.gov\/"
        }
    ]
}